pandoc_mermaid_filter.py
pandoc_mermaid_filter-0.1.0.dist-info/METADATA
pandoc_mermaid_filter-0.1.0.dist-info/RECORD
pandoc_mermaid_filter-0.1.0.dist-info/WHEEL
pandoc_mermaid_filter-0.1.0.dist-info/entry_points.txt
pandoc_mermaid_filter-0.1.0.dist-info/top_level.txt
