Metadata-Version: 2.1
Name: pandoc-mermaid-filter
Version: 0.1.0
Summary: Pandoc filter for mermaid code blocks
Home-page: https://github.com/timofurrer/pandoc-mermaid-filter
Author: Timo Furrer
Author-email: tuxtimo@gmail.com
License: MIT
Platform: UNKNOWN
Classifier: Development Status :: 5 - Production/Stable
Classifier: Intended Audience :: Developers
Classifier: License :: OSI Approved :: MIT License
Classifier: Natural Language :: English
Classifier: Operating System :: OS Independent
Classifier: Programming Language :: Python :: 2
Classifier: Programming Language :: Python :: 2.7
Classifier: Programming Language :: Python :: 3
Classifier: Programming Language :: Python :: 3.6
Classifier: Programming Language :: Python :: Implementation
Classifier: Programming Language :: Python :: Implementation :: CPython
Classifier: Topic :: Software Development :: Libraries :: Python Modules
Requires-Dist: pandocfilters
